HttpCtrl/__init__.py
HttpCtrl/http_handler.py
HttpCtrl/http_server.py
HttpCtrl/http_stub.py
HttpCtrl/internal_messages.py
HttpCtrl/request.py
HttpCtrl/request_storage.py
HttpCtrl/response.py
HttpCtrl/response_storage.py
HttpCtrl/utils/__init__.py
HttpCtrl/utils/logger.py
HttpCtrl/utils/singleton.py
robotframework_httpctrl-0.3.3.dist-info/licenses/LICENSE
robotframework_httpctrl-0.3.3.dist-info/METADATA
robotframework_httpctrl-0.3.3.dist-info/WHEEL
robotframework_httpctrl-0.3.3.dist-info/top_level.txt
robotframework_httpctrl-0.3.3.dist-info/RECORD
