Metadata-Version: 2.4
Name: robotframework-httpctrl
Version: 0.3.3
Summary: robotframework-httpctrl is a library for Robot Framework that provides HTTP/HTTPS client and HTTP server services.
Author-email: Andrei Novikov <spb.andr@yandex.ru>
Maintainer-email: Andrei Novikov <spb.andr@yandex.ru>
License-Expression: BSD-3-Clause
Project-URL: homepage, https://annoviko.github.io/robotframework-httpctrl/
Project-URL: source, https://github.com/annoviko/robotframework-httpctrl
Project-URL: documentation, https://annoviko.github.io/robotframework-httpctrl/
Project-URL: tracker, https://github.com/annoviko/robotframework-httpctrl/issues
Project-URL: changelog, https://github.com/annoviko/robotframework-httpctrl/blob/master/CHANGES
Keywords: httpctrl,http,https,robotframework,client,server,json,test,testing
Classifier: Development Status :: 5 - Production/Stable
Classifier: Intended Audience :: Developers
Classifier: Intended Audience :: Telecommunications Industry
Classifier: Natural Language :: English
Classifier: Topic :: Software Development :: Build Tools
Classifier: Programming Language :: Python :: 3 :: Only
Classifier: Topic :: Education
Classifier: Topic :: Internet :: WWW/HTTP
Classifier: Topic :: Internet :: WWW/HTTP :: HTTP Servers
Classifier: Topic :: Software Development :: Testing
Classifier: Framework :: Robot Framework :: Library
Requires-Python: >=3.8
License-File: LICENSE
Requires-Dist: robotframework
Dynamic: license-file
